CausalEGM/__init__.py
CausalEGM/__main__.py
CausalEGM/causalEGM.py
CausalEGM/cli.py
CausalEGM/model.py
CausalEGM/util.py
CausalEGM-0.3.3.dist-info/LICENSE
CausalEGM-0.3.3.dist-info/METADATA
CausalEGM-0.3.3.dist-info/WHEEL
CausalEGM-0.3.3.dist-info/entry_points.txt
CausalEGM-0.3.3.dist-info/top_level.txt
CausalEGM-0.3.3.dist-info/RECORD
