Metadata-Version: 2.1
Name: CausalEGM
Version: 0.3.3
Summary: CausalEGM: a general causal inference framework by encoding generative modeling
Home-page: https://github.com/SUwonglab/CausalEGM
Author: Qiao Liu
Author-email: liuqiao@stanford.edu
Classifier: Programming Language :: Python :: 3
Classifier: License :: OSI Approved :: MIT License
Classifier: Operating System :: OS Independent
Requires-Python: >=3.9
License-File: LICENSE
Requires-Dist: tensorflow (>=2.8.0)
Requires-Dist: scikit-learn
Requires-Dist: pandas
Requires-Dist: python-dateutil
